pymdb/__init__.py
pymdb/exceptions.py
pymdb/parser.py
pymdb/scraper.py
pymdb/utils.py
pymdb/models/__init__.py
pymdb/models/company.py
pymdb/models/name.py
pymdb/models/search.py
pymdb/models/title.py
pymdb/parser/__init__.py
pymdb/parser/pymdb_parser.py
pymdb/scraper/__init__.py
pymdb/scraper/pymdb_scraper.py
pymdb/utils/__init__.py
pymdb/utils/util.py
tests/__init__.py
tests/test_parser.py
tests/test_scraper.py
tests/test_utils.py
py_mdb-0.2.3.dist-info/LICENSE
py_mdb-0.2.3.dist-info/METADATA
py_mdb-0.2.3.dist-info/WHEEL
py_mdb-0.2.3.dist-info/top_level.txt
py_mdb-0.2.3.dist-info/RECORD
