Metadata-Version: 2.1
Name: py-mdb
Version: 0.2.3
Summary: Package for parsing IMDb datasets and scraping web pages
Home-page: https://github.com/zembrodt/pymdb
Author: Ryan Zembrodt
Author-email: ryan.zembrodt@gmail.com
License: UNKNOWN
Keywords: imdb,pymdb,movie,film,tv,series,show,episode,database,db,dataset,web scrape,scrape,actor,actress,director,writer,person,title,company,rating
Platform: UNKNOWN
Classifier: Programming Language :: Python
Classifier: Programming Language :: Python :: 3.9
Classifier: Programming Language :: Python :: 3.8
Classifier: Programming Language :: Python :: 3.7
Classifier: Programming Language :: Python :: 3.6
Classifier: License :: OSI Approved :: MIT License
Classifier: Operating System :: OS Independent
Requires-Python: >=3.6.0, <3.10.0
Requires-Dist: requests (>=2.25.1)
Requires-Dist: selectolax (>=0.2.11)
